weixin_search_mcp/__init__.py
weixin_search_mcp/main.py
weixin_search_mcp/tools/weixin_search.py
weixin_search_mcp-0.1.1.dist-info/METADATA
weixin_search_mcp-0.1.1.dist-info/WHEEL
weixin_search_mcp-0.1.1.dist-info/entry_points.txt
weixin_search_mcp-0.1.1.dist-info/top_level.txt
weixin_search_mcp-0.1.1.dist-info/RECORD
