Metadata-Version: 2.4
Name: weixin_search_mcp
Version: 0.1.1
Summary: 微信公众号内容搜索和获取工具
Author: mini
License-Expression: MIT
Classifier: Programming Language :: Python :: 3
Classifier: Programming Language :: Python :: 3.12
Classifier: Operating System :: OS Independent
Requires-Python: >=3.12
Requires-Dist: mcp[cli]>=1.6.0
Requires-Dist: fastmcp>=2.10.4
Requires-Dist: requests>=2.32.3
Requires-Dist: loguru>=0.7.2
Requires-Dist: python-dotenv>=1.1.1
Requires-Dist: fastapi>=0.110.0
Requires-Dist: uvicorn>=0.34.2
Requires-Dist: pydantic>=2.0.0
Requires-Dist: lxml>=4.9.3
Provides-Extra: dev
Requires-Dist: build>=1.2.2.post1; extra == "dev"
Requires-Dist: setuptools>=45; extra == "dev"
Requires-Dist: twine>=6.1.0; extra == "dev"
